reckomate_sdk/__init__.py
reckomate_sdk/client.py
reckomate_sdk/exceptions.py
reckomate_sdk/services/__init__.py
reckomate_sdk/services/admin_service.py
reckomate_sdk/services/audio_quiz_service.py
reckomate_sdk/services/chat_service.py
reckomate_sdk/services/firebase_service.py
reckomate_sdk/services/ingest_service.py
reckomate_sdk/services/mcq_service.py
reckomate_sdk/services/proxy_services.py
reckomate_sdk/services/qdrant_service.py
reckomate_sdk/services/rag_service.py
reckomate_sdk/services/scan_service.py
reckomate_sdk/services/user_service.py
reckomate_sdk/services/video_interview_service.py
reckomate_sdk/utils/__init__.py
reckomate_sdk/utils/headers.py
reckomate_sdk/utils/logger.py
reckomate_sdk/utils/retry.py
reckomate_sdk-1.0.8.dist-info/METADATA
reckomate_sdk-1.0.8.dist-info/WHEEL
reckomate_sdk-1.0.8.dist-info/top_level.txt
reckomate_sdk-1.0.8.dist-info/RECORD
